esper/__init__.py
esper/bootstrap.py
esper/main.py
esper/controllers/__init__.py
esper/controllers/base.py
esper/controllers/configure.py
esper/controllers/enums.py
esper/controllers/application/__init__.py
esper/controllers/application/application.py
esper/controllers/application/version.py
esper/controllers/commandsV2/__init__.py
esper/controllers/commandsV2/commandsV2.py
esper/controllers/content/__init__.py
esper/controllers/content/content.py
esper/controllers/device/__init__.py
esper/controllers/device/command.py
esper/controllers/device/device.py
esper/controllers/device/group_command.py
esper/controllers/device/install.py
esper/controllers/device/status.py
esper/controllers/enterprise/__init__.py
esper/controllers/enterprise/enterprise.py
esper/controllers/enterprise/group.py
esper/controllers/pipeline/__init__.py
esper/controllers/pipeline/execute.py
esper/controllers/pipeline/operation.py
esper/controllers/pipeline/pipeline.py
esper/controllers/pipeline/stage.py
esper/controllers/secureadb/__init__.py
esper/controllers/secureadb/secureadb.py
esper/controllers/telemetry/__init__.py
esper/controllers/telemetry/telemetry.py
esper/controllers/token/__init__.py
esper/controllers/token/token.py
esper/core/__init__.py
esper/core/exc.py
esper/core/output_handler.py
esper/core/version.py
esper/ext/__init__.py
esper/ext/api_client.py
esper/ext/certs.py
esper/ext/db_wrapper.py
esper/ext/forwarder.py
esper/ext/mediator.py
esper/ext/pipeline_api.py
esper/ext/relay.py
esper/ext/remoteadb_api.py
esper/ext/telemetry_api.py
esper/ext/utils.py
esper/plugins/__init__.py
esper/templates/__init__.py
esper/templates/command1.jinja2
esper/templates/creds.jinja2
espercli-0.0.14.dist-info/LICENSE
espercli-0.0.14.dist-info/LICENSE.md
espercli-0.0.14.dist-info/METADATA
espercli-0.0.14.dist-info/WHEEL
espercli-0.0.14.dist-info/entry_points.txt
espercli-0.0.14.dist-info/top_level.txt
espercli-0.0.14.dist-info/RECORD
