Metadata-Version: 2.1
Name: espercli
Version: 0.0.14
Summary: Esper CLI is Command line tool for the Esper APIs
Home-page: https://github.com/esper-io/esper-cli/
Author: Esper
Author-email: developer@esper.io
License: Apache 2.0
Platform: UNKNOWN
License-File: LICENSE
License-File: LICENSE.md
Requires-Dist: pip ==21.1
Requires-Dist: wheel
Requires-Dist: cement ==3.0.2
Requires-Dist: clint >=0.5.1
Requires-Dist: colorlog >=4.0.2
Requires-Dist: crayons >=0.2.0
Requires-Dist: esperclient >=0.1.2
Requires-Dist: jinja2 >=2.10.1
Requires-Dist: pyyaml >=5.4
Requires-Dist: requests ==2.32.2
Requires-Dist: tabulate >=0.8.3
Requires-Dist: tinydb >=3.13.0
Requires-Dist: tqdm >=4.32.1
Requires-Dist: pyOpenSSL ==24.1.0
